compass/core/__init__.py
compass/core/errors.py
compass/core/hierarchy.py
compass/core/interface.py
compass/core/logger.py
compass/core/logon.py
compass/core/people.py
compass/core/reports.py
compass/core/settings.py
compass/core/typing.py
compass/core/_scrapers/contact.py
compass/core/_scrapers/hierarchy.py
compass/core/_scrapers/member_profile.py
compass/core/_scrapers/reports.py
compass/core/_scrapers/role_detail.py
compass/core/schemas/hierarchy.py
compass/core/schemas/logon.py
compass/core/schemas/member.py
compass/core/types/hierarchy.py
compass/core/types/logon.py
compass/core/types/member.py
compass/core/types/reports.py
compass/core/util/auth_header.py
compass/core/util/client.py
compass/core/util/compass_helpers.py
compass/core/util/context_managers.py
compass/core/util/timeout.py
compass/core/util/type_coercion.py
compass_interface_core-0.27.0.dist-info/LICENSE
compass_interface_core-0.27.0.dist-info/WHEEL
compass_interface_core-0.27.0.dist-info/METADATA
compass_interface_core-0.27.0.dist-info/RECORD
